{
  "timestamp": "2026-03-30T06:16:53Z",
  "event_ts": "2026-03-30T06:16:36Z",
  "repo": "tekkura/sr-android",
  "event_name": "issues",
  "action": "opened",
  "actor": "topherbuckley",
  "run_id": "23730735211",
  "run_attempt": "1",
  "sender": {
    "login": "topherbuckley",
    "html_url": "https://github.com/topherbuckley"
  },
  "issue": {
    "number": 230,
    "title": "Replace comprehensiveDemo QR color inheritance placeholder with defined mating behavior",
    "state": "open",
    "html_url": "https://github.com/tekkura/sr-android/issues/230",
    "milestone": null
  },
  "comment": null,
  "milestone": null,
  "changes": null,
  "severity": "INFO",
  "target_url": "https://github.com/tekkura/sr-android/issues/230",
  "event_id": "da1ec342062cbc4ad6f53d1702eb223275de72791db739286bbc14b5c2092683"
}
