{
  "timestamp": "2026-07-13T03:56:18Z",
  "event_ts": "2026-07-13T03:56:00Z",
  "repo": "tekkura/sr-android",
  "event_name": "pull_request_review_comment",
  "action": "created",
  "actor": "GeorgeChernyshov",
  "run_id": "29222748083",
  "run_attempt": "1",
  "sender": {
    "login": "GeorgeChernyshov",
    "html_url": "https://github.com/GeorgeChernyshov"
  },
  "issue": null,
  "pull_request": {
    "number": 292,
    "title": "Storing QR codes in TimeStepData",
    "state": "open",
    "html_url": "https://github.com/tekkura/sr-android/pull/292",
    "milestone": {
      "number": 18,
      "title": "TimeStepData"
    }
  },
  "comment": {
    "id": 3567948313,
    "html_url": "https://github.com/tekkura/sr-android/pull/292#discussion_r3567948313",
    "created_at": "2026-07-13T03:56:00Z",
    "updated_at": "2026-07-13T03:56:00Z",
    "body": "#codex-reply resolved in [4a2b626](https://github.com/tekkura/sr-android/commit/4a2b626f51f148892722b170777df758aa47fe63)"
  },
  "milestone": null,
  "changes": null,
  "severity": "INFO",
  "target_url": "https://github.com/tekkura/sr-android/pull/292#discussion_r3567948313",
  "event_id": "9d927e50eaca192d1556b9de8ca0f8390bcdfc6647559a27739f51cdf34d4e0e"
}
